espn_scraper/__init__.py
espn_scraper-0.15.0.dist-info/LICENSE
espn_scraper-0.15.0.dist-info/METADATA
espn_scraper-0.15.0.dist-info/WHEEL
espn_scraper-0.15.0.dist-info/top_level.txt
espn_scraper-0.15.0.dist-info/RECORD
