Metadata-Version: 2.1
Name: espn_scraper
Version: 0.15.0
Summary: ESPN scraper for major sports
Home-page: http://github.com/andr3w321/espn_scraper
Author: Andrew Rennhack
Author-email: andr3w321@gmail.com
License: MIT
License-File: LICENSE
Requires-Dist: pytz
Requires-Dist: python-dateutil
Requires-Dist: requests
Requires-Dist: bs4
Requires-Dist: lxml
